pkgtoolkit/__init__.py
pkgtoolkit/globals.py
pkgtoolkit/parser/__init__.py
pkgtoolkit/parser/maven_parser.py
pkgtoolkit/parser/npm_parser.py
pkgtoolkit/parser/parser.py
pkgtoolkit/parser/parser_factory.py
pkgtoolkit/parser/pypi_parser.py
pkgtoolkit/scraper/__init__.py
pkgtoolkit/scraper/github_scraper.py
pkgtoolkit-0.1.1.dev0.dist-info/METADATA
pkgtoolkit-0.1.1.dev0.dist-info/WHEEL
pkgtoolkit-0.1.1.dev0.dist-info/top_level.txt
pkgtoolkit-0.1.1.dev0.dist-info/RECORD
