Metadata-Version: 2.1
Name: pkgtoolkit
Version: 0.1.1.dev0
Summary: Easy scraping and parsing of package dependencies.
Home-page: UNKNOWN
Author: UNKNOWN
Author-email: UNKNOWN
License: UNKNOWN
Platform: UNKNOWN
Requires-Dist: requests
Requires-Dist: nose
Requires-Dist: requirements-parser
